wildcard_integrations/__init__.py
wildcard_integrations/airtable/.gitignore
wildcard_integrations/airtable/.swagger-codegen/VERSION
wildcard_integrations/airtable/.swagger-codegen-ignore
wildcard_integrations/airtable/.travis.yml
wildcard_integrations/airtable/README.md
wildcard_integrations/airtable/__init__.py
wildcard_integrations/airtable/docs/AttachmentFieldIdOrNameUploadAttachmentBody.md
wildcard_integrations/airtable/docs/BaseIdTableIdOrNameBody.md
wildcard_integrations/airtable/docs/BaseIdTableIdOrNameBody1.md
wildcard_integrations/airtable/docs/BaseIdTableIdOrNameBody2.md
wildcard_integrations/airtable/docs/BaseIdTablesBody.md
wildcard_integrations/airtable/docs/BaseIdtableIdOrNamePerformUpsert.md
wildcard_integrations/airtable/docs/BaseIdtableIdOrNameRecords.md
wildcard_integrations/airtable/docs/BaseIdtableIdOrNameRecords1.md
wildcard_integrations/airtable/docs/BasesApi.md
wildcard_integrations/airtable/docs/CommentsApi.md
wildcard_integrations/airtable/docs/CommentsRowCommentIdBody.md
wildcard_integrations/airtable/docs/Field.md
wildcard_integrations/airtable/docs/FieldConfigRequest.md
wildcard_integrations/airtable/docs/FieldConfigResponse.md
wildcard_integrations/airtable/docs/FieldModel.md
wildcard_integrations/airtable/docs/FieldOptions.md
wildcard_integrations/airtable/docs/FieldOptions1.md
wildcard_integrations/airtable/docs/FieldOptions10.md
wildcard_integrations/airtable/docs/FieldOptions10Choices.md
wildcard_integrations/airtable/docs/FieldOptions11.md
wildcard_integrations/airtable/docs/FieldOptions12.md
wildcard_integrations/airtable/docs/FieldOptions12Choices.md
wildcard_integrations/airtable/docs/FieldOptions13.md
wildcard_integrations/airtable/docs/FieldOptions14.md
wildcard_integrations/airtable/docs/FieldOptions15.md
wildcard_integrations/airtable/docs/FieldOptions16.md
wildcard_integrations/airtable/docs/FieldOptions16Choices.md
wildcard_integrations/airtable/docs/FieldOptions17.md
wildcard_integrations/airtable/docs/FieldOptions18.md
wildcard_integrations-0.1.5.dist-info/METADATA
wildcard_integrations-0.1.5.dist-info/WHEEL
wildcard_integrations-0.1.5.dist-info/RECORD
