Metadata-Version: 2.1
Name: wildcard-integrations
Version: 0.1.5
Summary: API client integrations for the Wildcard ecosystem
License: Elastic-2.0
Author: Kaushik
Author-email: kaushik@wild-card.ai
Requires-Python: >=3.9
Classifier: License :: Other/Proprietary License
Classifier: Programming Language :: Python :: 3
Classifier: Programming Language :: Python :: 3.9
Classifier: Programming Language :: Python :: 3.10
Classifier: Programming Language :: Python :: 3.11
Classifier: Programming Language :: Python :: 3.12
Classifier: Programming Language :: Python :: 3.13
Provides-Extra: airtable
Provides-Extra: gmail
Requires-Dist: certifi (>=2017.4.17) ; extra == "airtable"
Requires-Dist: python-dateutil (>=2.1) ; extra == "airtable"
Requires-Dist: six (>=1.10) ; extra == "airtable"
Requires-Dist: urllib3 (>=1.25.3) ; extra == "airtable"
